dash_functional_component/LifecycleEvents.py
dash_functional_component/PropsInjector.py
dash_functional_component/__init__.py
dash_functional_component/_imports_.py
dash_functional_component/dash_functional_component.min.js
dash_functional_component/dash_functional_component.min.js.map
dash_functional_component/metadata.json
dash_functional_component/package-info.json
dash_functional_component-0.0.4.dist-info/LICENSE
dash_functional_component-0.0.4.dist-info/METADATA
dash_functional_component-0.0.4.dist-info/WHEEL
dash_functional_component-0.0.4.dist-info/top_level.txt
dash_functional_component-0.0.4.dist-info/RECORD
