Metadata-Version: 2.1
Name: dash_functional_component
Version: 0.0.4
Summary: Project Description
Author: kikyous <kikyous@163.com>
License: MIT
Classifier: Framework :: Dash
License-File: LICENSE
